ophelos_sdk/__init__.py
ophelos_sdk/auth.py
ophelos_sdk/client.py
ophelos_sdk/exceptions.py
ophelos_sdk/http_client.py
ophelos_sdk/py.typed
ophelos_sdk/webhooks.py
ophelos_sdk/models/__init__.py
ophelos_sdk/models/base.py
ophelos_sdk/models/communication.py
ophelos_sdk/models/customer.py
ophelos_sdk/models/debt.py
ophelos_sdk/models/invoice.py
ophelos_sdk/models/organisation.py
ophelos_sdk/models/pagination.py
ophelos_sdk/models/payment.py
ophelos_sdk/models/payout.py
ophelos_sdk/models/tenant.py
ophelos_sdk/models/webhook.py
ophelos_sdk/resources/__init__.py
ophelos_sdk/resources/base.py
ophelos_sdk/resources/communications.py
ophelos_sdk/resources/contact_details.py
ophelos_sdk/resources/customers.py
ophelos_sdk/resources/debts.py
ophelos_sdk/resources/invoices.py
ophelos_sdk/resources/line_items.py
ophelos_sdk/resources/organisations.py
ophelos_sdk/resources/payment_plans.py
ophelos_sdk/resources/payments.py
ophelos_sdk/resources/payouts.py
ophelos_sdk/resources/tenants.py
ophelos_sdk/resources/webhooks.py
ophelos_sdk-1.6.0.dist-info/licenses/LICENSE
ophelos_sdk-1.6.0.dist-info/METADATA
ophelos_sdk-1.6.0.dist-info/WHEEL
ophelos_sdk-1.6.0.dist-info/top_level.txt
ophelos_sdk-1.6.0.dist-info/RECORD
